atsphinx/footnotes.py
atsphinx_footnotes-0.3.1.dist-info/licenses/LICENSE
atsphinx_footnotes-0.3.1.dist-info/WHEEL
atsphinx_footnotes-0.3.1.dist-info/METADATA
atsphinx_footnotes-0.3.1.dist-info/RECORD
