Metadata-Version: 2.4
Name: atsphinx-footnotes
Version: 0.3.1
Summary: Powered footnotes extension for Sphinx.
Author-email: Kazuya Takei <myself@attakei.net>
Requires-Python: >= 3.8
Classifier: Development Status :: 4 - Beta
Classifier: Framework :: Sphinx
Classifier: Framework :: Sphinx :: Extension
Classifier: Intended Audience :: Developers
Classifier: License :: OSI Approved :: Apache Software License
Classifier: Programming Language :: Python :: 3.8
Classifier: Programming Language :: Python :: 3.9
Classifier: Programming Language :: Python :: 3.10
Classifier: Programming Language :: Python :: 3.11
Classifier: Programming Language :: Python :: 3.12
Classifier: Programming Language :: Python :: 3.13
Classifier: Topic :: Documentation :: Sphinx
License-File: LICENSE
Requires-Dist: sphinx
Project-URL: Home, https://github.com/atsphinx/footnotes
